{"test0": {"url": "https://google.com"}, "file0": {"file": "file01_mWWz_fABgRc-W2s4VHF6PQ.gif"}, "test1": {"url": "https://yahoo.com"}, "test2": {"url": "https://bing.com"}, "dfnd": {"url": "https://defund.netlify.app"}, "lsn": {"url": "https://lensin-beta-64c959.netlify.app/"}, "416451": {"url": "https://lensin-beta-64c959.netlify.app/"}, "goog": {"url": "https://google.com"}, "file1": {"file": "file1WhatsApp_Video_2021-12-23_at_4.03.50_PM.gif"}, "y": {"url": "https://yahoo.com"}, "34": {"url": "https://yahoo.com"}}